string2eval/__init__.py
string2eval/syntax_encoder.py
string2eval_discord-0.0.5.dist-info/METADATA
string2eval_discord-0.0.5.dist-info/WHEEL
string2eval_discord-0.0.5.dist-info/top_level.txt
string2eval_discord-0.0.5.dist-info/RECORD
