Metadata-Version: 2.1
Name: string2eval-discord
Version: 0.0.5
Summary: UNKNOWN
Home-page: UNKNOWN
Author: LuigiMoment31
License: MIT
Platform: UNKNOWN
Classifier: Programming Language :: Python :: 3
Classifier: License :: OSI Approved :: MIT License
Requires-Python: >=3.6
Requires-Dist: discord.py
